scapywrapper/__init__.py
scapywrapper/pcapFileParser/__init__.py
scapywrapper/pcapFileParser/pcapFileParser.py
scapywrapper/tests/__init__.py
scapywrapper/tests/main.py
scapywrapper/utilities/__init__.py
scapywrapper/utilities/loggable.py
scapywrapper-1.0.dist-info/LICENSE
scapywrapper-1.0.dist-info/METADATA
scapywrapper-1.0.dist-info/WHEEL
scapywrapper-1.0.dist-info/top_level.txt
scapywrapper-1.0.dist-info/RECORD
