Metadata-Version: 2.1
Name: scapywrapper
Version: 1.0
Summary: Basic Python wrapper to extend the built-in capabilities of the scapy package
Home-page: https://github.com/guyavrah1986/scapywrapper.git
Author: Guy Avraham
Author-email: guyavrah1986@gmail.com
License: GPL-2.0
Platform: UNKNOWN
Requires-Dist: scapy
